[
    {
        "tafseer_id": 10,
        "tafseer_name": "Yusuf Ali",
        "ayah_url": "/quran/56/1/",
        "ayah_number": 1,
        "text": "When the Event inevitable cometh to pass,"
    },
    {
        "tafseer_id": 10,
        "tafseer_name": "Yusuf Ali",
        "ayah_url": "/quran/56/2/",
        "ayah_number": 2,
        "text": "Then will no (soul) entertain falsehood concerning its coming."
    },
    {
        "tafseer_id": 10,
        "tafseer_name": "Yusuf Ali",
        "ayah_url": "/quran/56/3/",
        "ayah_number": 3,
        "text": "(Many) will it bring low; (many) will it exalt;"
    },
    {
        "tafseer_id": 10,
        "tafseer_name": "Yusuf Ali",
        "ayah_url": "/quran/56/4/",
        "ayah_number": 4,
        "text": "When the earth shall be shaken to its depths,"
    },
    {
        "tafseer_id": 10,
        "tafseer_name": "Yusuf Ali",
        "ayah_url": "/quran/56/5/",
        "ayah_number": 5,
        "text": "And the mountains shall be crumbled to atoms,"
    },
    {
        "tafseer_id": 10,
        "tafseer_name": "Yusuf Ali",
        "ayah_url": "/quran/56/6/",
        "ayah_number": 6,
        "text": "Becoming dust scattered abroad,"
    },
    {
        "tafseer_id": 10,
        "tafseer_name": "Yusuf Ali",
        "ayah_url": "/quran/56/7/",
        "ayah_number": 7,
        "text": "And ye shall be sorted out into three classes."
    },
    {
        "tafseer_id": 10,
        "tafseer_name": "Yusuf Ali",
        "ayah_url": "/quran/56/8/",
        "ayah_number": 8,
        "text": "Then (there will be) the Companions of the Right Hand;- What will be the Companions of the Right Hand?"
    },
    {
        "tafseer_id": 10,
        "tafseer_name": "Yusuf Ali",
        "ayah_url": "/quran/56/9/",
        "ayah_number": 9,
        "text": "And the Companions of the Left Hand,- what will be the Companions of the Left Hand?"
    },
    {
        "tafseer_id": 10,
        "tafseer_name": "Yusuf Ali",
        "ayah_url": "/quran/56/10/",
        "ayah_number": 10,
        "text": "And those Foremost (in Faith) will be Foremost (in the Hereafter)."
    },
    {
        "tafseer_id": 10,
        "tafseer_name": "Yusuf Ali",
        "ayah_url": "/quran/56/11/",
        "ayah_number": 11,
        "text": "These will be those Nearest to Allah:"
    },
    {
        "tafseer_id": 10,
        "tafseer_name": "Yusuf Ali",
        "ayah_url": "/quran/56/12/",
        "ayah_number": 12,
        "text": "In Gardens of Bliss:"
    },
    {
        "tafseer_id": 10,
        "tafseer_name": "Yusuf Ali",
        "ayah_url": "/quran/56/13/",
        "ayah_number": 13,
        "text": "A number of people from those of old,"
    },
    {
        "tafseer_id": 10,
        "tafseer_name": "Yusuf Ali",
        "ayah_url": "/quran/56/14/",
        "ayah_number": 14,
        "text": "And a few from those of later times."
    },
    {
        "tafseer_id": 10,
        "tafseer_name": "Yusuf Ali",
        "ayah_url": "/quran/56/15/",
        "ayah_number": 15,
        "text": "(They will be) on Thrones encrusted (with gold and precious stones),"
    },
    {
        "tafseer_id": 10,
        "tafseer_name": "Yusuf Ali",
        "ayah_url": "/quran/56/16/",
        "ayah_number": 16,
        "text": "Reclining on them, facing each other."
    },
    {
        "tafseer_id": 10,
        "tafseer_name": "Yusuf Ali",
        "ayah_url": "/quran/56/17/",
        "ayah_number": 17,
        "text": "Round about them will (serve) youths of perpetual (freshness),"
    },
    {
        "tafseer_id": 10,
        "tafseer_name": "Yusuf Ali",
        "ayah_url": "/quran/56/18/",
        "ayah_number": 18,
        "text": "With goblets, (shining) beakers, and cups (filled) out of clear-flowing fountains:"
    },
    {
        "tafseer_id": 10,
        "tafseer_name": "Yusuf Ali",
        "ayah_url": "/quran/56/19/",
        "ayah_number": 19,
        "text": "No after-ache will they receive therefrom, nor will they suffer intoxication:"
    },
    {
        "tafseer_id": 10,
        "tafseer_name": "Yusuf Ali",
        "ayah_url": "/quran/56/20/",
        "ayah_number": 20,
        "text": "And with fruits, any that they may select:"
    },
    {
        "tafseer_id": 10,
        "tafseer_name": "Yusuf Ali",
        "ayah_url": "/quran/56/21/",
        "ayah_number": 21,
        "text": "And the flesh of fowls, any that they may desire."
    },
    {
        "tafseer_id": 10,
        "tafseer_name": "Yusuf Ali",
        "ayah_url": "/quran/56/22/",
        "ayah_number": 22,
        "text": "And (there will be) Companions with beautiful, big, and lustrous eyes,-"
    },
    {
        "tafseer_id": 10,
        "tafseer_name": "Yusuf Ali",
        "ayah_url": "/quran/56/23/",
        "ayah_number": 23,
        "text": "Like unto Pearls well-guarded."
    },
    {
        "tafseer_id": 10,
        "tafseer_name": "Yusuf Ali",
        "ayah_url": "/quran/56/24/",
        "ayah_number": 24,
        "text": "A Reward for the deeds of their past (life)."
    },
    {
        "tafseer_id": 10,
        "tafseer_name": "Yusuf Ali",
        "ayah_url": "/quran/56/25/",
        "ayah_number": 25,
        "text": "Not frivolity will they hear therein, nor any taint of ill,-"
    },
    {
        "tafseer_id": 10,
        "tafseer_name": "Yusuf Ali",
        "ayah_url": "/quran/56/26/",
        "ayah_number": 26,
        "text": "Only the saying, \"Peace! Peace\"."
    },
    {
        "tafseer_id": 10,
        "tafseer_name": "Yusuf Ali",
        "ayah_url": "/quran/56/27/",
        "ayah_number": 27,
        "text": "The Companions of the Right Hand,- what will be the Companions of the Right Hand?"
    },
    {
        "tafseer_id": 10,
        "tafseer_name": "Yusuf Ali",
        "ayah_url": "/quran/56/28/",
        "ayah_number": 28,
        "text": "(They will be) among Lote-trees without thorns,"
    },
    {
        "tafseer_id": 10,
        "tafseer_name": "Yusuf Ali",
        "ayah_url": "/quran/56/29/",
        "ayah_number": 29,
        "text": "Among Talh trees with flowers (or fruits) piled one above another,-"
    },
    {
        "tafseer_id": 10,
        "tafseer_name": "Yusuf Ali",
        "ayah_url": "/quran/56/30/",
        "ayah_number": 30,
        "text": "In shade long-extended,"
    },
    {
        "tafseer_id": 10,
        "tafseer_name": "Yusuf Ali",
        "ayah_url": "/quran/56/31/",
        "ayah_number": 31,
        "text": "By water flowing constantly,"
    },
    {
        "tafseer_id": 10,
        "tafseer_name": "Yusuf Ali",
        "ayah_url": "/quran/56/32/",
        "ayah_number": 32,
        "text": "And fruit in abundance."
    },
    {
        "tafseer_id": 10,
        "tafseer_name": "Yusuf Ali",
        "ayah_url": "/quran/56/33/",
        "ayah_number": 33,
        "text": "Whose season is not limited, nor (supply) forbidden,"
    },
    {
        "tafseer_id": 10,
        "tafseer_name": "Yusuf Ali",
        "ayah_url": "/quran/56/34/",
        "ayah_number": 34,
        "text": "And on Thrones (of Dignity), raised high."
    },
    {
        "tafseer_id": 10,
        "tafseer_name": "Yusuf Ali",
        "ayah_url": "/quran/56/35/",
        "ayah_number": 35,
        "text": "We have created (their Companions) of special creation."
    },
    {
        "tafseer_id": 10,
        "tafseer_name": "Yusuf Ali",
        "ayah_url": "/quran/56/36/",
        "ayah_number": 36,
        "text": "And made them virgin - pure (and undefiled), -"
    },
    {
        "tafseer_id": 10,
        "tafseer_name": "Yusuf Ali",
        "ayah_url": "/quran/56/37/",
        "ayah_number": 37,
        "text": "Beloved (by nature), equal in age,-"
    },
    {
        "tafseer_id": 10,
        "tafseer_name": "Yusuf Ali",
        "ayah_url": "/quran/56/38/",
        "ayah_number": 38,
        "text": "For the Companions of the Right Hand."
    },
    {
        "tafseer_id": 10,
        "tafseer_name": "Yusuf Ali",
        "ayah_url": "/quran/56/39/",
        "ayah_number": 39,
        "text": "A (goodly) number from those of old,"
    },
    {
        "tafseer_id": 10,
        "tafseer_name": "Yusuf Ali",
        "ayah_url": "/quran/56/40/",
        "ayah_number": 40,
        "text": "And a (goodly) number from those of later times."
    },
    {
        "tafseer_id": 10,
        "tafseer_name": "Yusuf Ali",
        "ayah_url": "/quran/56/41/",
        "ayah_number": 41,
        "text": "The Companions of the Left Hand,- what will be the Companions of the Left Hand?"
    },
    {
        "tafseer_id": 10,
        "tafseer_name": "Yusuf Ali",
        "ayah_url": "/quran/56/42/",
        "ayah_number": 42,
        "text": "(They will be) in the midst of a Fierce Blast of Fire and in Boiling Water,"
    },
    {
        "tafseer_id": 10,
        "tafseer_name": "Yusuf Ali",
        "ayah_url": "/quran/56/43/",
        "ayah_number": 43,
        "text": "And in the shades of Black Smoke:"
    },
    {
        "tafseer_id": 10,
        "tafseer_name": "Yusuf Ali",
        "ayah_url": "/quran/56/44/",
        "ayah_number": 44,
        "text": "Nothing (will there be) to refresh, nor to please:"
    },
    {
        "tafseer_id": 10,
        "tafseer_name": "Yusuf Ali",
        "ayah_url": "/quran/56/45/",
        "ayah_number": 45,
        "text": "For that they were wont to be indulged, before that, in wealth (and luxury),"
    },
    {
        "tafseer_id": 10,
        "tafseer_name": "Yusuf Ali",
        "ayah_url": "/quran/56/46/",
        "ayah_number": 46,
        "text": "And persisted obstinately in wickedness supreme!"
    },
    {
        "tafseer_id": 10,
        "tafseer_name": "Yusuf Ali",
        "ayah_url": "/quran/56/47/",
        "ayah_number": 47,
        "text": "And they used to say, \"What! when we die and become dust and bones, shall we then indeed be raised up again?-"
    },
    {
        "tafseer_id": 10,
        "tafseer_name": "Yusuf Ali",
        "ayah_url": "/quran/56/48/",
        "ayah_number": 48,
        "text": "\"(We) and our fathers of old?\""
    },
    {
        "tafseer_id": 10,
        "tafseer_name": "Yusuf Ali",
        "ayah_url": "/quran/56/49/",
        "ayah_number": 49,
        "text": "Say: \"Yea, those of old and those of later times,"
    },
    {
        "tafseer_id": 10,
        "tafseer_name": "Yusuf Ali",
        "ayah_url": "/quran/56/50/",
        "ayah_number": 50,
        "text": "\"All will certainly be gathered together for the meeting appointed for a Day well-known."
    },
    {
        "tafseer_id": 10,
        "tafseer_name": "Yusuf Ali",
        "ayah_url": "/quran/56/51/",
        "ayah_number": 51,
        "text": "\"Then will ye truly,- O ye that go wrong, and treat (Truth) as Falsehood!-"
    },
    {
        "tafseer_id": 10,
        "tafseer_name": "Yusuf Ali",
        "ayah_url": "/quran/56/52/",
        "ayah_number": 52,
        "text": "\"Ye will surely taste of the Tree of Zaqqum."
    },
    {
        "tafseer_id": 10,
        "tafseer_name": "Yusuf Ali",
        "ayah_url": "/quran/56/53/",
        "ayah_number": 53,
        "text": "\"Then will ye fill your insides therewith,"
    },
    {
        "tafseer_id": 10,
        "tafseer_name": "Yusuf Ali",
        "ayah_url": "/quran/56/54/",
        "ayah_number": 54,
        "text": "\"And drink Boiling Water on top of it:"
    },
    {
        "tafseer_id": 10,
        "tafseer_name": "Yusuf Ali",
        "ayah_url": "/quran/56/55/",
        "ayah_number": 55,
        "text": "\"Indeed ye shall drink like diseased camels raging with thirst!\""
    },
    {
        "tafseer_id": 10,
        "tafseer_name": "Yusuf Ali",
        "ayah_url": "/quran/56/56/",
        "ayah_number": 56,
        "text": "Such will be their entertainment on the Day of Requital!"
    },
    {
        "tafseer_id": 10,
        "tafseer_name": "Yusuf Ali",
        "ayah_url": "/quran/56/57/",
        "ayah_number": 57,
        "text": "It is We Who have created you: why will ye not witness the Truth?"
    },
    {
        "tafseer_id": 10,
        "tafseer_name": "Yusuf Ali",
        "ayah_url": "/quran/56/58/",
        "ayah_number": 58,
        "text": "Do ye then see?- The (human Seed) that ye throw out,-"
    },
    {
        "tafseer_id": 10,
        "tafseer_name": "Yusuf Ali",
        "ayah_url": "/quran/56/59/",
        "ayah_number": 59,
        "text": "Is it ye who create it, or are We the Creators?"
    },
    {
        "tafseer_id": 10,
        "tafseer_name": "Yusuf Ali",
        "ayah_url": "/quran/56/60/",
        "ayah_number": 60,
        "text": "We have decreed Death to be your common lot, and We are not to be frustrated"
    },
    {
        "tafseer_id": 10,
        "tafseer_name": "Yusuf Ali",
        "ayah_url": "/quran/56/61/",
        "ayah_number": 61,
        "text": "from changing your Forms and creating you (again) in (forms) that ye know not."
    },
    {
        "tafseer_id": 10,
        "tafseer_name": "Yusuf Ali",
        "ayah_url": "/quran/56/62/",
        "ayah_number": 62,
        "text": "And ye certainly know already the first form of creation: why then do ye not celebrate His praises?"
    },
    {
        "tafseer_id": 10,
        "tafseer_name": "Yusuf Ali",
        "ayah_url": "/quran/56/63/",
        "ayah_number": 63,
        "text": "See ye the seed that ye sow in the ground?"
    },
    {
        "tafseer_id": 10,
        "tafseer_name": "Yusuf Ali",
        "ayah_url": "/quran/56/64/",
        "ayah_number": 64,
        "text": "Is it ye that cause it to grow, or are We the Cause?"
    },
    {
        "tafseer_id": 10,
        "tafseer_name": "Yusuf Ali",
        "ayah_url": "/quran/56/65/",
        "ayah_number": 65,
        "text": "Were it Our Will, We could crumble it to dry powder, and ye would be left in wonderment,"
    },
    {
        "tafseer_id": 10,
        "tafseer_name": "Yusuf Ali",
        "ayah_url": "/quran/56/66/",
        "ayah_number": 66,
        "text": "(Saying), \"We are indeed left with debts (for nothing):"
    },
    {
        "tafseer_id": 10,
        "tafseer_name": "Yusuf Ali",
        "ayah_url": "/quran/56/67/",
        "ayah_number": 67,
        "text": "\"Indeed are we shut out (of the fruits of our labour)\""
    },
    {
        "tafseer_id": 10,
        "tafseer_name": "Yusuf Ali",
        "ayah_url": "/quran/56/68/",
        "ayah_number": 68,
        "text": "See ye the water which ye drink?"
    },
    {
        "tafseer_id": 10,
        "tafseer_name": "Yusuf Ali",
        "ayah_url": "/quran/56/69/",
        "ayah_number": 69,
        "text": "Do ye bring it down (in rain) from the cloud or do We?"
    },
    {
        "tafseer_id": 10,
        "tafseer_name": "Yusuf Ali",
        "ayah_url": "/quran/56/70/",
        "ayah_number": 70,
        "text": "Were it Our Will, We could make it salt (and unpalatable): then why do ye not give thanks?"
    },
    {
        "tafseer_id": 10,
        "tafseer_name": "Yusuf Ali",
        "ayah_url": "/quran/56/71/",
        "ayah_number": 71,
        "text": "See ye the Fire which ye kindle?"
    },
    {
        "tafseer_id": 10,
        "tafseer_name": "Yusuf Ali",
        "ayah_url": "/quran/56/72/",
        "ayah_number": 72,
        "text": "Is it ye who grow the tree which feeds the fire, or do We grow it?"
    },
    {
        "tafseer_id": 10,
        "tafseer_name": "Yusuf Ali",
        "ayah_url": "/quran/56/73/",
        "ayah_number": 73,
        "text": "We have made it a memorial (of Our handiwork), and an article of comfort and convenience for the denizens of deserts."
    },
    {
        "tafseer_id": 10,
        "tafseer_name": "Yusuf Ali",
        "ayah_url": "/quran/56/74/",
        "ayah_number": 74,
        "text": "Then celebrate with praises the name of thy Lord, the Supreme!"
    },
    {
        "tafseer_id": 10,
        "tafseer_name": "Yusuf Ali",
        "ayah_url": "/quran/56/75/",
        "ayah_number": 75,
        "text": "Furthermore I call to witness the setting of the Stars,-"
    },
    {
        "tafseer_id": 10,
        "tafseer_name": "Yusuf Ali",
        "ayah_url": "/quran/56/76/",
        "ayah_number": 76,
        "text": "And that is indeed a mighty adjuration if ye but knew,-"
    },
    {
        "tafseer_id": 10,
        "tafseer_name": "Yusuf Ali",
        "ayah_url": "/quran/56/77/",
        "ayah_number": 77,
        "text": "That this is indeed a qur'an Most Honourable,"
    },
    {
        "tafseer_id": 10,
        "tafseer_name": "Yusuf Ali",
        "ayah_url": "/quran/56/78/",
        "ayah_number": 78,
        "text": "In Book well-guarded,"
    },
    {
        "tafseer_id": 10,
        "tafseer_name": "Yusuf Ali",
        "ayah_url": "/quran/56/79/",
        "ayah_number": 79,
        "text": "Which none shall touch but those who are clean:"
    },
    {
        "tafseer_id": 10,
        "tafseer_name": "Yusuf Ali",
        "ayah_url": "/quran/56/80/",
        "ayah_number": 80,
        "text": "A Revelation from the Lord of the Worlds."
    },
    {
        "tafseer_id": 10,
        "tafseer_name": "Yusuf Ali",
        "ayah_url": "/quran/56/81/",
        "ayah_number": 81,
        "text": "Is it such a Message that ye would hold in light esteem?"
    },
    {
        "tafseer_id": 10,
        "tafseer_name": "Yusuf Ali",
        "ayah_url": "/quran/56/82/",
        "ayah_number": 82,
        "text": "And have ye made it your livelihood that ye should declare it false?"
    },
    {
        "tafseer_id": 10,
        "tafseer_name": "Yusuf Ali",
        "ayah_url": "/quran/56/83/",
        "ayah_number": 83,
        "text": "Then why do ye not (intervene) when (the soul of the dying man) reaches the throat,-"
    },
    {
        "tafseer_id": 10,
        "tafseer_name": "Yusuf Ali",
        "ayah_url": "/quran/56/84/",
        "ayah_number": 84,
        "text": "And ye the while (sit) looking on,-"
    },
    {
        "tafseer_id": 10,
        "tafseer_name": "Yusuf Ali",
        "ayah_url": "/quran/56/85/",
        "ayah_number": 85,
        "text": "But We are nearer to him than ye, and yet see not,-"
    },
    {
        "tafseer_id": 10,
        "tafseer_name": "Yusuf Ali",
        "ayah_url": "/quran/56/86/",
        "ayah_number": 86,
        "text": "Then why do ye not,- If you are exempt from (future) account,-"
    },
    {
        "tafseer_id": 10,
        "tafseer_name": "Yusuf Ali",
        "ayah_url": "/quran/56/87/",
        "ayah_number": 87,
        "text": "Call back the soul, if ye are true (in the claim of independence)?"
    },
    {
        "tafseer_id": 10,
        "tafseer_name": "Yusuf Ali",
        "ayah_url": "/quran/56/88/",
        "ayah_number": 88,
        "text": "Thus, then, if he be of those Nearest to Allah,"
    },
    {
        "tafseer_id": 10,
        "tafseer_name": "Yusuf Ali",
        "ayah_url": "/quran/56/89/",
        "ayah_number": 89,
        "text": "(There is for him) Rest and Satisfaction, and a Garden of Delights."
    },
    {
        "tafseer_id": 10,
        "tafseer_name": "Yusuf Ali",
        "ayah_url": "/quran/56/90/",
        "ayah_number": 90,
        "text": "And if he be of the Companions of the Right Hand,"
    },
    {
        "tafseer_id": 10,
        "tafseer_name": "Yusuf Ali",
        "ayah_url": "/quran/56/91/",
        "ayah_number": 91,
        "text": "(For him is the salutation), \"Peace be unto thee\", from the Companions of the Right Hand."
    },
    {
        "tafseer_id": 10,
        "tafseer_name": "Yusuf Ali",
        "ayah_url": "/quran/56/92/",
        "ayah_number": 92,
        "text": "And if he be of those who treat (Truth) as Falsehood, who go wrong,"
    },
    {
        "tafseer_id": 10,
        "tafseer_name": "Yusuf Ali",
        "ayah_url": "/quran/56/93/",
        "ayah_number": 93,
        "text": "For him is Entertainment with Boiling Water."
    },
    {
        "tafseer_id": 10,
        "tafseer_name": "Yusuf Ali",
        "ayah_url": "/quran/56/94/",
        "ayah_number": 94,
        "text": "And burning in Hell-Fire."
    },
    {
        "tafseer_id": 10,
        "tafseer_name": "Yusuf Ali",
        "ayah_url": "/quran/56/95/",
        "ayah_number": 95,
        "text": "Verily, this is the Very Truth and Certainly."
    },
    {
        "tafseer_id": 10,
        "tafseer_name": "Yusuf Ali",
        "ayah_url": "/quran/56/96/",
        "ayah_number": 96,
        "text": "So celebrate with praises the name of thy Lord, the Supreme."
    }
]