[
    {
        "tafseer_id": 10,
        "tafseer_name": "Yusuf Ali",
        "ayah_url": "/quran/95/1/",
        "ayah_number": 1,
        "text": "By the Fig and the Olive,"
    },
    {
        "tafseer_id": 10,
        "tafseer_name": "Yusuf Ali",
        "ayah_url": "/quran/95/2/",
        "ayah_number": 2,
        "text": "And the Mount of Sinai,"
    },
    {
        "tafseer_id": 10,
        "tafseer_name": "Yusuf Ali",
        "ayah_url": "/quran/95/3/",
        "ayah_number": 3,
        "text": "And this City of security,-"
    },
    {
        "tafseer_id": 10,
        "tafseer_name": "Yusuf Ali",
        "ayah_url": "/quran/95/4/",
        "ayah_number": 4,
        "text": "We have indeed created man in the best of moulds,"
    },
    {
        "tafseer_id": 10,
        "tafseer_name": "Yusuf Ali",
        "ayah_url": "/quran/95/5/",
        "ayah_number": 5,
        "text": "Then do We abase him (to be) the lowest of the low,-"
    },
    {
        "tafseer_id": 10,
        "tafseer_name": "Yusuf Ali",
        "ayah_url": "/quran/95/6/",
        "ayah_number": 6,
        "text": "Except such as believe and do righteous deeds: For they shall have a reward unfailing."
    },
    {
        "tafseer_id": 10,
        "tafseer_name": "Yusuf Ali",
        "ayah_url": "/quran/95/7/",
        "ayah_number": 7,
        "text": "Then what can, after this, contradict thee, as to the judgment (to come)?"
    },
    {
        "tafseer_id": 10,
        "tafseer_name": "Yusuf Ali",
        "ayah_url": "/quran/95/8/",
        "ayah_number": 8,
        "text": "Is not Allah the wisest of judges?"
    }
]